[
    {
        "reviewer": {
            "displayName": "<a href='https://www.linkedin.com/in/zeeldesai700/' target='_blank'>ZEEL DESAI</a>"
        },
        "starRating": "FIVE",
        "comment": "He is very enthusiasm person and he is always ready to learn new things.\nI am very glad that you are exploring a new things and become an inspiration to others.",
        "createTime": "2023-06-05T16:42:01.820273Z",
        "updateTime": "2023-06-05T16:42:01.820273Z",
        "reviewReply": {
            "comment": "Thankyou mam 🤩 sounds good 😃 I am happy to know I am able to \ninspiring someone.",
            "updateTime": "2023-06-06T02:11:37.235085Z"
        },
        "name": "accounts/108679175144070620594/locations/14395317695646119136/reviews/ChZDSUhNMG9nS0VJQ0FnSUR4OHYtZFRBEAE"
    },
    {
        "reviewer": {
            "displayName": "<a href='https://www.linkedin.com/in/akanksha-sharma-5abb1517b/' target='_blank'>Akanksha Sharma</a>"
        },
        "starRating": "FIVE",
        "comment": "Best in what he does. Passionate about his work and deliver quality work everytime. One can easily count on him for any kind of technical work.",
        "createTime": "2023-06-05T14:22:46.007351Z",
        "updateTime": "2023-06-05T14:25:21.512820Z",
        "reviewReply": {
            "comment": "Thanks a lot such a wonderful 🤩  review",
            "updateTime": "2023-06-05T15:54:18.271328Z"
        },
        "name": "accounts/108679175144070620594/locations/14395317695646119136/reviews/ChdDSUhNMG9nS0VJQ0FnSUR4OHF6Umd3RRAB"
    },
    {
        "reviewer": {
            "displayName": "Anuj Rajawat"
        },
        "starRating": "FIVE",
        "comment": "Such a great work and you are a good listener ❤️",
        "createTime": "2023-06-05T11:56:33.046609Z",
        "updateTime": "2023-06-05T11:56:33.046609Z",
        "reviewReply": {
            "comment": "Wow 🤩 really ",
            "updateTime": "2023-06-05T15:54:58.621131Z"
        },
        "name": "accounts/108679175144070620594/locations/14395317695646119136/reviews/ChZDSUhNMG9nS0VJQ0FnSUR4c29iZVpBEAE"
    },
    {
        "reviewer": {
            "displayName": "Vikas Yadav"
        },
        "starRating": "FIVE",
        "comment": "Very friendly  nature",
        "createTime": "2019-10-09T09:29:35.297185Z",
        "updateTime": "2023-06-05T11:33:40.109111Z",
        "reviewReply": {
            "comment": "Thanks Mr. Vikash",
            "updateTime": "2019-10-09T10:42:02.451860Z"
        },
        "name": "accounts/108679175144070620594/locations/14395317695646119136/reviews/ChZDSUhNMG9nS0VJQ0FnSUMwMC15bENnEAE"
    },
    {
        "reviewer": {
            "displayName": "<a href='https://www.linkedin.com/in/bhavin-rathod-8bb728152/' target='_blank'>Bhavin Rathod</a>"
        },
        "starRating": "FIVE",
        "comment": "He is a good man, very energetic and enthusiastic for programming.",
        "createTime": "2023-06-05T11:30:25.677783Z",
        "updateTime": "2023-06-05T11:30:25.677783Z",
        "reviewReply": {
            "comment": "Thanks Bhavin working with you as developer that one is great experience.",
            "updateTime": "2023-06-05T11:48:13.731398Z"
        },
        "name": "accounts/108679175144070620594/locations/14395317695646119136/reviews/ChZDSUhNMG9nS0VJQ0FnSUR4c3Z5dVpnEAE"
    },
    {
        "reviewer": {
            "displayName": "Pankaj Kumar Saini"
        },
        "starRating": "FIVE",
        "comment": "Ready to face any kind of problems, ready to help at any time, overall kind person.",
        "createTime": "2019-11-06T09:28:00.104601Z",
        "updateTime": "2023-04-01T07:15:23.318877Z",
        "reviewReply": {
            "comment": "Thank you for the positive feedback, Pankaj! It means a lot to me to hear that you found me helpful and kind. If you ever need assistance in the future, don't hesitate to reach out. I'll be happy to help in any way I can :) ",
            "updateTime": "2023-04-01T10:02:53.513333Z"
        },
        "name": "accounts/108679175144070620594/locations/14395317695646119136/reviews/ChZDSUhNMG9nS0VJQ0FnSUQwbnVPU0hnEAE"
    },
    {
        "reviewer": {
            "displayName": "<a href='https://www.linkedin.com/in/krishna-tiwari-621009182/' target='_blank'>Krishna Tiwari</a>"
        },
        "starRating": "FIVE",
        "comment": "One of the best developer in IT whole IT industry.\nI have used his skills many times in some softwares and website technicalities & he always did well.",
        "createTime": "2019-11-06T07:19:15.685164Z",
        "updateTime": "2022-11-14T07:29:38.755057Z",
        "reviewReply": {
            "comment": "Hi Krishna thanks for sharing your review.\nI am also grateful to god they have giving me this skill that help you. ",
            "updateTime": "2022-11-14T07:39:18.117660Z"
        },
        "name": "accounts/108679175144070620594/locations/14395317695646119136/reviews/ChZDSUhNMG9nS0VJQ0FnSUQwbnJHa0hREAE"
    },
    {
        "reviewer": {
            "displayName": "Rohit Jadon"
        },
        "starRating": "FIVE",
        "comment": "Well done brother",
        "createTime": "2019-11-13T17:26:26.093741Z",
        "updateTime": "2019-11-13T17:26:26.093741Z",
        "name": "accounts/108679175144070620594/locations/14395317695646119136/reviews/ChdDSUhNMG9nS0VJQ0FnSUQwbGNLbl93RRAB"
    },
    {
        "reviewer": {
            "displayName": "Sani Tiwari"
        },
        "starRating": "FIVE",
        "comment": "Awesome developer",
        "createTime": "2019-11-12T04:21:59.509065Z",
        "updateTime": "2019-11-12T04:21:59.509065Z",
        "name": "accounts/108679175144070620594/locations/14395317695646119136/reviews/ChdDSUhNMG9nS0VJQ0FnSUQwLWZHMTRnRRAB"
    },
    {
        "reviewer": {
            "displayName": "<a href='https://www.linkedin.com/in/nipun-arora-a0080a140/' target='_blank'>Nipun Arora</a>"
        },
        "starRating": "FIVE",
        "comment": "He is best web developer",
        "createTime": "2019-11-06T08:41:01.245398Z",
        "updateTime": "2019-11-06T08:41:59.509259Z",
        "name": "accounts/108679175144070620594/locations/14395317695646119136/reviews/ChZDSUhNMG9nS0VJQ0FnSUQwbm8zWWRREAE"
    },
    {
        "reviewer": {
            "displayName": "<a href='https://www.linkedin.com/in/sachin-yadav-75a47815b/' target='_blank'>Sachin Yadav</a>"
        },
        "starRating": "FIVE",
        "comment": "Best develeper,good programmer",
        "createTime": "2019-11-06T08:35:39.959651Z",
        "updateTime": "2019-11-06T08:35:39.959651Z",
        "name": "accounts/108679175144070620594/locations/14395317695646119136/reviews/ChdDSUhNMG9nS0VJQ0FnSUQwbnJYYjJRRRAB"
    },
    {
        "reviewer": {
            "displayName": "manish nursing service"
        },
        "starRating": "FIVE",
        "comment": "Good mere bhai",
        "createTime": "2019-10-21T02:41:40.643547Z",
        "updateTime": "2019-10-21T02:42:00.273301Z",
        "name": "accounts/108679175144070620594/locations/14395317695646119136/reviews/ChdDSUhNMG9nS0VJQ0FnSUQwNk1HSTlnRRAB"
    },
    {
        "reviewer": {
            "displayName": "Jayesh Soni"
        },
        "starRating": "FIVE",
        "comment": "Friendly Behaviour...Like a Friend😎",
        "createTime": "2019-10-13T13:46:16.974078Z",
        "updateTime": "2019-10-13T13:46:16.974078Z",
        "reviewReply": {
            "comment": "thanks Mr. jayesh",
            "updateTime": "2019-10-13T14:20:31.825054Z"
        },
        "name": "accounts/108679175144070620594/locations/14395317695646119136/reviews/ChZDSUhNMG9nS0VJQ0FnSUMwbDRyeERBEAE"
    },
    {
        "reviewer": {
            "displayName": "Sonu Pal (S.p.singh)"
        },
        "starRating": "FIVE",
        "comment": "Brilliant teacher nice behaviour nice person one of the brilliant man on earth",
        "createTime": "2019-10-13T11:20:02.688937Z",
        "updateTime": "2019-10-13T11:25:15.648087Z",
        "reviewReply": {
            "comment": "thanks brother,",
            "updateTime": "2019-10-13T11:27:12.726602Z"
        },
        "name": "accounts/108679175144070620594/locations/14395317695646119136/reviews/ChZDSUhNMG9nS0VJQ0FnSUMwNTh2YWJnEAE"
    },
    {
        "reviewer": {
            "displayName": "Anany dixit"
        },
        "starRating": "FIVE",
        "comment": "He is brilliant student. Quick learner and responsible student.",
        "createTime": "2019-10-09T15:53:43.059062Z",
        "updateTime": "2019-10-09T15:54:22.795576Z",
        "reviewReply": {
            "comment": "Thank you sir",
            "updateTime": "2019-10-10T03:16:05.007845Z"
        },
        "name": "accounts/108679175144070620594/locations/14395317695646119136/reviews/ChdDSUhNMG9nS0VJQ0FnSUMwczhHcXpBRRAB"
    },
    {
        "reviewer": {
            "displayName": "sorav kirar"
        },
        "starRating": "FIVE",
        "comment": "Good person",
        "createTime": "2019-10-09T15:21:02.836817Z",
        "updateTime": "2019-10-09T15:21:02.836817Z",
        "reviewReply": {
            "comment": "thanks",
            "updateTime": "2019-10-10T03:16:25.772349Z"
        },
        "name": "accounts/108679175144070620594/locations/14395317695646119136/reviews/ChdDSUhNMG9nS0VJQ0FnSUMwczZiajFRRRAB"
    },
    {
        "reviewer": {
            "displayName": "Akash Goud"
        },
        "starRating": "FIVE",
        "comment": "HE IS  BEST IT PERSON WE CALL HIM AS IT",
        "createTime": "2019-10-09T15:13:35.393182Z",
        "updateTime": "2019-10-09T15:15:26.877272Z",
        "name": "accounts/108679175144070620594/locations/14395317695646119136/reviews/ChdDSUhNMG9nS0VJQ0FnSUMwc19xeC1BRRAB"
    },
    {
        "reviewer": {
            "displayName": "sourav Kirar"
        },
        "starRating": "FIVE",
        "comment": "Nice",
        "createTime": "2020-10-08T08:43:13.350586Z",
        "updateTime": "2020-10-08T08:43:13.350586Z",
        "reviewReply": {
            "comment": "👍🏻",
            "updateTime": "2020-10-08T08:56:39.282006Z"
        },
        "name": "accounts/108679175144070620594/locations/14395317695646119136/reviews/ChdDSUhNMG9nS0VJQ0FnSURDdll6WTN3RRAB"
    },
    {
        "reviewer": {
            "displayName": "Gourav Kirar"
        },
        "starRating": "FIVE",
        "comment": "You are a very nice person.......Always help everyone...I am happy to have a friend like you....♥",
        "createTime": "2020-10-08T04:48:37.518029Z",
        "updateTime": "2020-10-08T04:48:37.518029Z",
        "reviewReply": {
            "comment": "Thankyou bhai 😍",
            "updateTime": "2020-10-08T05:53:14.852004Z"
        },
        "name": "accounts/108679175144070620594/locations/14395317695646119136/reviews/ChdDSUhNMG9nS0VJQ0FnSURDM1pPbnp3RRAB"
    },
    {
        "reviewer": {
            "displayName": "Shubham Jain"
        },
        "starRating": "FIVE",
        "comment": "Best develovper",
        "createTime": "2020-09-04T07:12:48.035573Z",
        "updateTime": "2020-09-04T07:12:48.035573Z",
        "name": "accounts/108679175144070620594/locations/14395317695646119136/reviews/ChdDSUhNMG9nS0VJQ0FnSUNDNjhYcDNRRRAB"
    },
    {
        "reviewer": {
            "displayName": "Khatik Satish"
        },
        "starRating": "FIVE",
        "comment": "Good developer",
        "createTime": "2020-02-02T10:08:14.874476Z",
        "updateTime": "2020-02-02T10:08:14.874476Z",
        "name": "accounts/108679175144070620594/locations/14395317695646119136/reviews/ChZDSUhNMG9nS0VJQ0FnSUNzcnVYalJBEAE"
    },
    {
        "reviewer": {
            "displayName": "Dhoni Karish (Karish)"
        },
        "starRating": "FIVE",
        "comment": "He is good  person",
        "createTime": "2019-10-09T14:00:46.764342Z",
        "updateTime": "2019-10-09T14:00:46.764342Z",
        "reviewReply": {
            "comment": "thanks",
            "updateTime": "2019-10-09T14:50:54.245750Z"
        },
        "name": "accounts/108679175144070620594/locations/14395317695646119136/reviews/ChZDSUhNMG9nS0VJQ0FnSUMwajVQMFFnEAE"
    },
    {
        "reviewer": {
            "displayName": "Janak Yadav"
        },
        "starRating": "FIVE",
        "comment": "यह बहुत ही शांत है एंव महनती भी है\n\n(Translated by Google)\nIt is very quiet and hard working too.",
        "createTime": "2019-10-09T13:44:24.936968Z",
        "updateTime": "2019-10-09T13:44:24.936968Z",
        "name": "accounts/108679175144070620594/locations/14395317695646119136/reviews/ChZDSUhNMG9nS0VJQ0FnSUMwei1MSkpnEAE"
    },
    {
        "reviewer": {
            "displayName": "Ajay Rajput005"
        },
        "starRating": "FIVE",
        "comment": "Very good teacher",
        "createTime": "2019-10-09T13:43:06.575698Z",
        "updateTime": "2019-10-09T13:43:06.575698Z",
        "reviewReply": {
            "comment": "thanks brother",
            "updateTime": "2019-10-09T13:44:29.596346Z"
        },
        "name": "accounts/108679175144070620594/locations/14395317695646119136/reviews/ChZDSUhNMG9nS0VJQ0FnSUMwc19DeFJBEAE"
    },
    {
        "reviewer": {
            "displayName": "CHIRAG YADAV"
        },
        "starRating": "FIVE",
        "comment": "Very good teacher and cool person😊😊☺",
        "createTime": "2019-10-09T10:24:41.704963Z",
        "updateTime": "2019-10-09T10:24:41.704963Z",
        "reviewReply": {
            "comment": "thanks brother",
            "updateTime": "2019-10-09T10:41:11.994941Z"
        },
        "name": "accounts/108679175144070620594/locations/14395317695646119136/reviews/ChdDSUhNMG9nS0VJQ0FnSUMwMDZhZTdnRRAB"
    },
    {
        "reviewer": {
            "displayName": "Rishabh Dixit"
        },
        "starRating": "FIVE",
        "comment": "brilliant teacher",
        "createTime": "2019-10-09T05:27:30.996694Z",
        "updateTime": "2019-10-09T05:27:30.996694Z",
        "reviewReply": {
            "comment": "thanks brother",
            "updateTime": "2019-10-09T10:42:15.651754Z"
        },
        "name": "accounts/108679175144070620594/locations/14395317695646119136/reviews/ChdDSUhNMG9nS0VJQ0FnSUMwa19MOXh3RRAB"
    }
]